{
	"format_version": "1.8.0",
	"animations": {
		"animation.parasaurolophus.walk": {
			"loop": true,
			"animation_length": 2.08,
			"anim_time_update": "query.modified_distance_moved",
			"bones": {
				"leftArm": {
					"rotation": {
						"0.0": [0, 0, 0],
						"0.52": [-15, 0, 0],
						"1.04": [0, 0, 0],
						"1.56": [15, 0, 0],
						"2.08": [0, 0, 0]
					}
				},
				"rightArm": {
					"rotation": {
						"0.0": [0, 0, 0],
						"0.52": [15, 0, 0],
						"1.04": [0, 0, 0],
						"1.56": [-15, 0, 0],
						"2.08": [0, 0, 0]
					}
				},
				"leftLeg": {
					"rotation": {
						"0.0": [0, 0, 0],
						"0.52": [15, 0, 0],
						"1.04": [0, 0, 0],
						"1.56": [-15, 0, 0],
						"2.08": [0, 0, 0]
					}
				},
				"rightLeg": {
					"rotation": {
						"0.0": [0, 0, 0],
						"0.52": [-15, 0, 0],
						"1.04": [0, 0, 0],
						"1.56": [15, 0, 0],
						"2.08": [0, 0, 0]
					}
				}
			}
		},
		"animation.parasaurolophus.harvest": {
			"animation_length": 0.52,
			"bones": {
				"neck": {
					"rotation": {
						"0.0": [0, 0, 0],
						"0.28": [60, 0, 0],
						"0.52": [0, 0, 0]
					}
				}
			}
		},
		"animation.parasaurolophus.attack": {
			"animation_length": 0.52,
			"bones": {
				"neck": {
					"rotation": {
						"0.0": [0, 0, 0],
						"0.28": [60, 0, 0],
						"0.52": [0, 0, 0]
					}
				}
			}
		},
		"animation.parasaurolophus.sitting": {
			"loop": true,
			"bones": {
				"body": {
					"position": [0, -6, 0]
				},
				"leftArm": {
					"rotation": [-45, 0, 0],
					"position": [0, 1.25, 0]
				},
				"leftShoulder": {
					"rotation": [-45, 0, 0]
				},
				"rightArm": {
					"rotation": [-45, 0, 0],
					"position": [0, 1.25, 0]
				},
				"rightShoulder": {
					"rotation": [-45, 0, 0]
				},
				"leftLeg": {
					"position": [0, -4, 0]
				},
				"rightLeg": {
					"position": [0, -4, 0]
				},
				"rightShin": {
					"position": [0, 4, 0]
				},
				"leftShin": {
					"position": [0, 4, 0]
				}
			}
		},
		"animation.parasaurolophus.call": {
			"animation_length": 1.04,
			"bones": {
				"body": {
					"rotation": {
						"0.0": [0, 0, 0],
						"0.52": [-20, 0, 0],
						"0.76": [-20, 0, 0],
						"1.04": [0, 0, 0]
					}
				},
				"neck": {
					"rotation": {
						"0.0": [0, 0, 0],
						"0.52": ["10-Math.clamp(query.target_x_rotation, -10, 10)", 0, 0],
						"0.76": ["10-Math.clamp(query.target_x_rotation, -10, 10)", 0, 0],
						"1.04": [0, 0, 0]
					}
				},
				"head": {
					"rotation": {
						"0.0": [0, 0, 0],
						"0.52": [10, 0, 0],
						"0.76": [-10, 0, 0],
						"1.04": [0, 0, 0]
					}
				},
				"leftShoulder": {
					"rotation": {
						"0.0": [0, 0, 0],
						"0.52": [20, 0, 0],
						"0.76": [20, 0, 0],
						"1.04": [0, 0, 0]
					}
				},
				"rightShoulder": {
					"rotation": {
						"0.0": [0, 0, 0],
						"0.52": [20, 0, 0],
						"0.76": [20, 0, 0],
						"1.04": [0, 0, 0]
					}
				},
				"lowerJaw": {
					"rotation": {
						"0.52": [0, 0, 0],
						"0.76": [30, 0, 0],
						"1.04": [0, 0, 0]
					}
				},
				"tail0": {
					"rotation": {
						"0.0": [0, 0, 0],
						"0.52": [12.5, 0, 0],
						"0.76": [12.5, 0, 0],
						"1.04": [0, 0, 0]
					}
				}
			}
		},
		"animation.parasaurolophus.blow": {
			"animation_length": 1.76,
			"bones": {
				"body": {
					"rotation": {
						"0.0": [0, 0, 0],
						"0.24": [-12.5, 0, 0],
						"0.48": [10, 0, 0],
						"1.52": [10, 0, 0],
						"1.76": [0, 0, 0]
					}
				},
				"neck": {
					"rotation": {
						"0.0": [0, 0, 0],
						"0.24": [12.5, 0, 0],
						"0.48": [5, 0, 0],
						"0.56": [4.92442, 0.86717, -9.96271],
						"0.72": [4.92123, -0.86301, 9.96554],
						"0.88": [4.92442, 0.86717, -9.96271],
						"1.04": [4.92123, -0.86301, 9.96554],
						"1.2": [4.92442, 0.86717, -9.96271],
						"1.36": [4.92123, -0.86301, 9.96554],
						"1.44": [5, 0, 0],
						"1.52": [5, 0, 0],
						"1.76": [0, 0, 0]
					}
				},
				"lowerJaw": {
					"rotation": {
						"0.24": [0, 0, 0],
						"0.36": [22.5, 0, 0],
						"1.44": [22.5, 0, 0],
						"1.52": [0, 0, 0]
					}
				},
				"leftArm": {
					"rotation": {
						"0.36": [0, 0, 0],
						"0.48": [7.5, 0, 0],
						"1.52": [7.5, 0, 0],
						"1.76": [0, 0, 0]
					}
				},
				"leftShoulder": {
					"rotation": {
						"0.0": [0, 0, 0],
						"0.24": [30, 0, 0],
						"1.52": [30, 0, 0],
						"1.76": [0, 0, 0]
					}
				},
				"rightArm": {
					"rotation": {
						"0.36": [0, 0, 0],
						"0.48": [7.5, 0, 0],
						"1.52": [7.5, 0, 0],
						"1.76": [0, 0, 0]
					}
				},
				"rightShoulder": {
					"rotation": {
						"0.0": [0, 0, 0],
						"0.24": [30, 0, 0],
						"1.52": [30, 0, 0],
						"1.76": [0, 0, 0]
					}
				}
			}
		},
		"animation.parasaurolophus.use_blow_p1": {
			"animation_length": 5,
			"bones": {
				"body": {
					"rotation": ["-Math.clamp(use_blow * 0.125, 0, 12.5)", 0, 0]
				},
				"neck": {
					"rotation": ["Math.clamp(use_blow * 0.125, 0, 12.5)", 0, 0]
				},
				"leftShoulder": {
					"rotation": ["Math.clamp(use_blow * 0.30, 0, 30)", 0, 0]
				},
				"rightShoulder": {
					"rotation": ["Math.clamp(use_blow * 0.30, 0, 30)", 0, 0]
				}
			}
		},
		"animation.parasaurolophus.use_blow_p1_hold": {
			"loop": true,
			"bones": {
				"body": {
					"rotation": [-12.5, 0, 0]
				},
				"neck": {
					"rotation": [12.5, 0, 0]
				},
				"lowerJaw": {
					"rotation": [0, 0, 0]
				},
				"leftShoulder": {
					"rotation": [30, 0, 0]
				},
				"rightShoulder": {
					"rotation": [30, 0, 0]
				}
			}
		},
		"animation.parasaurolophus.use_blow_p2": {
			"animation_length": 1.52,
			"bones": {
				"body": {
					"rotation": {
						"0.0": [-12.5, 0, 0],
						"0.24": [10, 0, 0],
						"1.28": [10, 0, 0],
						"1.52": [0, 0, 0]
					}
				},
				"neck": {
					"rotation": {
						"0.0": [12.5, 0, 0],
						"0.24": [5, 0, 0],
						"0.32": [4.92442, 0.86717, -9.96271],
						"0.48": [4.92123, -0.86301, 9.96554],
						"0.64": [4.92442, 0.86717, -9.96271],
						"0.8": [4.92123, -0.86301, 9.96554],
						"0.96": [4.92442, 0.86717, -9.96271],
						"1.12": [4.92123, -0.86301, 9.96554],
						"1.2": [5, 0, 0],
						"1.28": [5, 0, 0],
						"1.52": [0, 0, 0]
					}
				},
				"lowerJaw": {
					"rotation": {
						"0.0": [0, 0, 0],
						"0.12": [22.5, 0, 0],
						"1.2": [22.5, 0, 0],
						"1.28": [0, 0, 0]
					}
				},
				"leftArm": {
					"rotation": {
						"0.0": [0, 0, 0],
						"0.12": [0, 0, 0],
						"0.24": [7.5, 0, 0],
						"1.28": [7.5, 0, 0],
						"1.52": [0, 0, 0]
					}
				},
				"leftShoulder": {
					"rotation": {
						"0.0": [30, 0, 0],
						"1.28": [30, 0, 0],
						"1.52": [0, 0, 0]
					}
				},
				"rightArm": {
					"rotation": {
						"0.0": [0, 0, 0],
						"0.12": [0, 0, 0],
						"0.24": [7.5, 0, 0],
						"1.28": [7.5, 0, 0],
						"1.52": [0, 0, 0]
					}
				},
				"rightShoulder": {
					"rotation": {
						"0.0": [30, 0, 0],
						"1.28": [30, 0, 0],
						"1.52": [0, 0, 0]
					}
				}
			}
		},
		"animation.parasaurolophus.incapacitated": {
			"loop": true,
			"bones": {
				"base": {
					"position": [0, -8, 0]
				},
				"neck": {
					"rotation": [27.5, 0, 0]
				},
				"leftArm": {
					"rotation": [-120.84447, 39.28675, 1.72951],
					"position": [1, 0, 0]
				},
				"leftShoulder": {
					"rotation": [32.5, 0, 0]
				},
				"rightArm": {
					"rotation": [-120.84447, -39.2868, 1.72951],
					"position": [-1, 0, 0]
				},
				"rightShoulder": {
					"rotation": [32.5, 0, 0]
				},
				"leftLeg": {
					"rotation": [90, 0, 0],
					"position": [0, -1.5, 0]
				},
				"leftShin": {
					"rotation": [-5, 0, 0],
					"position": [0, -2.4, -3.4]
				},
				"rightLeg": {
					"rotation": [90, 0, 0],
					"position": [0, -1.5, 0]
				},
				"rightShin": {
					"rotation": [-5, 0, 0],
					"position": [0, -2.4, -3.4]
				}
			}
		},
		"animation.parasaurolophus.use_head_type_move": {
			"animation_length": 0.5,
			"bones": {
				"body": {
					"rotation": {
						"0.0": [0, 0, 0],
						"0.25": [-12.5, 0, 0],
						"0.3125": [0, 0, 0],
						"0.5": [0, 0, 0]
					}
				},
				"neck": {
					"rotation": {
						"0.0": [0, 0, 0],
						"0.25": [12.5, 0, 0],
						"0.3125": [42.5, 0, 0],
						"0.5": [0, 0, 0]
					}
				},
				"leftArm": {
					"rotation": {
						"0.0": [0, 0, 0],
						"0.25": [22.5, 0, 0],
						"0.3125": [22.5, 0, 0],
						"0.5": [0, 0, 0]
					}
				},
				"rightArm": {
					"rotation": {
						"0.0": [0, 0, 0],
						"0.25": [22.5, 0, 0],
						"0.3125": [22.5, 0, 0],
						"0.5": [0, 0, 0]
					}
				}
			}
		},
		"animation.parasaurolophus.use_status_type_move": {
			"animation_length": 2,
			"bones": {
				"body": {
					"rotation": {
						"0.0": [0, 0, 0],
						"0.25": [7.5, 0, 0],
						"0.75": [-15, 0, 0],
						"0.875": [0, 0, 0],
						"1.75": [0, 0, 0],
						"2.0": [0, 0, 0]
					}
				},
				"neck": {
					"rotation": {
						"0.0": [0, 0, 0],
						"0.25": [30, 0, 0],
						"0.875": [30, 0, 0],
						"1.0": [29.40842, -6.21271, 10.86815],
						"1.125": [29.78798, 3.74501, -6.50239],
						"1.25": [29.40842, -6.21271, 10.86815],
						"1.375": [29.78798, 3.74501, -6.50239],
						"1.5": [29.40842, -6.21271, 10.86815],
						"1.625": [29.78798, 3.74501, -6.50239],
						"1.75": [29.79, 3.75, -6.5],
						"2.0": [0, 0, 0]
					}
				},
				"lowerJaw": {
					"rotation": {
						"0.75": [0, 0, 0],
						"0.875": [22.5, 0, 0],
						"1.625": [22.5, 0, 0],
						"1.75": [0, 0, 0],
						"2.0": [0, 0, 0]
					}
				},
				"leftArm": {
					"rotation": {
						"0.0": [0, 0, 0],
						"0.25": [17.5, 0, 0],
						"1.75": [17.5, 0, 0],
						"2.0": [0, 0, 0]
					}
				},
				"rightArm": {
					"rotation": {
						"0.0": [0, 0, 0],
						"0.25": [17.5, 0, 0],
						"1.75": [17.5, 0, 0],
						"2.0": [0, 0, 0]
					}
				}
			}
		},
		"animation.parasaurolophus.use_blow_type_move": {
			"animation_length": 1.75,
			"bones": {
				"body": {
					"rotation": {
						"0.0": [0, 0, 0],
						"0.25": [-12.5, 0, 0],
						"0.5": [10, 0, 0],
						"1.5": [10, 0, 0],
						"1.75": [0, 0, 0]
					}
				},
				"neck": {
					"rotation": {
						"0.0": [0, 0, 0],
						"0.25": [12.5, 0, 0],
						"0.5": [5, 0, 0],
						"0.625": [4.88206, -1.08089, 12.45392],
						"0.75": [4.87982, 1.08083, -12.45792],
						"0.875": [4.88206, -1.08089, 12.45392],
						"1.0": [4.87982, 1.08083, -12.45792],
						"1.125": [4.88206, -1.08089, 12.45392],
						"1.25": [4.87982, 1.08083, -12.45792],
						"1.375": [4.88206, -1.08089, 12.45392],
						"1.5": [0, 0, 0],
						"1.75": [0, 0, 0]
					}
				},
				"lowerJaw": {
					"rotation": {
						"0.375": [0, 0, 0],
						"0.5": [22.5, 0, 0],
						"1.375": [22.5, 0, 0],
						"1.5": [0, 0, 0],
						"1.75": [0, 0, 0]
					}
				},
				"leftArm": {
					"rotation": {
						"0.375": [0, 0, 0],
						"0.5": [7.5, 0, 0],
						"1.5": [7.5, 0, 0],
						"1.75": [0, 0, 0]
					}
				},
				"leftShoulder": {
					"rotation": {
						"0.0": [0, 0, 0],
						"0.25": [30, 0, 0],
						"1.5": [30, 0, 0],
						"1.75": [0, 0, 0]
					}
				},
				"rightArm": {
					"rotation": {
						"0.375": [0, 0, 0],
						"0.5": [7.5, 0, 0],
						"1.5": [7.5, 0, 0],
						"1.75": [0, 0, 0]
					}
				},
				"rightShoulder": {
					"rotation": {
						"0.0": [0, 0, 0],
						"0.25": [30, 0, 0],
						"1.5": [30, 0, 0],
						"1.75": [0, 0, 0]
					}
				}
			}
		},
		"animation.parasaurolophus.use_charged_blow_type_move_pt1": {
			"animation_length": 5,
			"bones": {
				"body": {
					"rotation": ["creature_move_use * -0.125", 0, 0]
				},
				"neck": {
					"rotation": ["creature_move_use * 0.125", 0, 0]
				},
				"leftShoulder": {
					"rotation": ["creature_move_use * 0.3", 0, 0]
				},
				"rightShoulder": {
					"rotation": ["creature_move_use * 0.3", 0, 0]
				}
			}
		},
		"animation.parasaurolophus.use_charged_blow_type_move_pt1_hold": {
			"loop": true,
			"bones": {
				"body": {
					"rotation": [-12.5, 0, 0]
				},
				"neck": {
					"rotation": [12.5, 0, 0]
				},
				"leftShoulder": {
					"rotation": [30, 0, 0]
				},
				"rightShoulder": {
					"rotation": [30, 0, 0]
				}
			}
		},
		"animation.parasaurolophus.use_charged_blow_type_move_pt2": {
			"animation_length": 1.5,
			"bones": {
				"body": {
					"rotation": {
						"0.0": ["creature_move_use * -0.125", 0, 0],
						"0.25": [10, 0, 0],
						"1.25": [10, 0, 0],
						"1.5": [0, 0, 0]
					}
				},
				"neck": {
					"rotation": {
						"0.0": ["creature_move_use * 0.125", 0, 0],
						"0.25": [5, 0, 0],
						"0.375": [4.88206, -1.08089, 12.45392],
						"0.5": [4.87982, 1.08083, -12.45792],
						"0.625": [4.88206, -1.08089, 12.45392],
						"0.75": [4.87982, 1.08083, -12.45792],
						"0.875": [4.88206, -1.08089, 12.45392],
						"1.0": [4.87982, 1.08083, -12.45792],
						"1.125": [4.88206, -1.08089, 12.45392],
						"1.25": [0, 0, 0],
						"1.5": [0, 0, 0]
					}
				},
				"lowerJaw": {
					"rotation": {
						"0.0": [0, 0, 0],
						"0.25": [22.5, 0, 0],
						"1.125": [22.5, 0, 0],
						"1.25": [0, 0, 0],
						"1.5": [0, 0, 0]
					}
				},
				"leftArm": {
					"rotation": {
						"0.0": [0, 0, 0],
						"0.25": [7.5, 0, 0],
						"1.25": [7.5, 0, 0],
						"1.5": [0, 0, 0]
					}
				},
				"leftShoulder": {
					"rotation": {
						"0.0": ["creature_move_use * 0.3", 0, 0],
						"1.25": ["creature_move_use * 0.3", 0, 0],
						"1.5": [0, 0, 0]
					}
				},
				"rightArm": {
					"rotation": {
						"0.0": [0, 0, 0],
						"0.25": [7.5, 0, 0],
						"1.25": [7.5, 0, 0],
						"1.5": [0, 0, 0]
					}
				},
				"rightShoulder": {
					"rotation": {
						"0.0": ["creature_move_use * 0.3", 0, 0],
						"1.25": ["creature_move_use * 0.3", 0, 0],
						"1.5": [0, 0, 0]
					}
				}
			}
		},
		"animation.parasaurolophus.warn": {
			"animation_length": 2.25,
			"bones": {
				"body": {
					"rotation": {
						"0.0": [0, 0, 0],
						"0.25": [-20, 0, 0],
						"0.5": [-20, 0, 0],
						"1.0": [-20.44582, 11.73507, -4.3361],
						"1.5": [-20.44582, -11.73507, 4.3361],
						"2.0": [-20, 0, 0],
						"2.25": [0, 0, 0]
					}
				},
				"neck": {
					"rotation": {
						"0.0": [0, 0, 0],
						"0.25": [10, 0, 0],
						"0.5": [10, 0, 0],
						"2.0": [10, 0, 0],
						"2.25": [0, 0, 0]
					}
				},
				"head": {
					"rotation": {
						"0.0": [0, 0, 0],
						"0.25": [10, 0, 0],
						"0.5": [-10, 0, 0],
						"2.0": [-10, 0, 0],
						"2.25": [0, 0, 0]
					}
				},
				"leftShoulder": {
					"rotation": {
						"0.0": [0, 0, 0],
						"0.25": [20, 0, 0],
						"0.5": [20, 0, 0],
						"2.0": [20, 0, 0],
						"2.25": [0, 0, 0]
					}
				},
				"rightShoulder": {
					"rotation": {
						"0.0": [0, 0, 0],
						"0.25": [20, 0, 0],
						"0.5": [20, 0, 0],
						"2.0": [20, 0, 0],
						"2.25": [0, 0, 0]
					}
				},
				"lowerJaw": {
					"rotation": {
						"0.25": [0, 0, 0],
						"0.5": [30, 0, 0],
						"2.0": [30, 0, 0],
						"2.25": [0, 0, 0]
					}
				},
				"tail0": {
					"rotation": {
						"0.0": [0, 0, 0],
						"0.125": [0, 0, 0],
						"0.25": [12.5, 0, 0],
						"0.5": [12.5, 0, 0],
						"2.0": [12.5, 0, 0],
						"2.25": [0, 0, 0]
					}
				}
			}
		}
	}
}